[
  {
    "userId": "user_001",
    "name": "Amit Sharma",
    "email": "amit123sharma@gmail.com",
    "address": "GBZAAM3FEDEIKMSODD36SR2F4D327VO3IAEZFWJMK3W5GHWQYNVKKTMI",
    "action": "Contributed 79 XLM to Group #4",
    "hash": "80851879f679b270cdb0752543b53f0e624a45b77f6167147d32370246fbce33",
    "date": "2026-07-17",
    "feedback": "Automated testnet Saver profile contribution successfully verified."
  },
  {
    "userId": "user_002",
    "name": "Neha Patel",
    "email": "neha.patel9876@gmail.com",
    "address": "GAE7SGGYB7ESDP7UPTTJNZ7K5ZFWUTERLGV7JYNPIIEZH3JE2SBKBO7A",
    "action": "Contributed 79 XLM to Group #4",
    "hash": "ce5da3402d80d3a3bdb02ba26fe75e765adb3a6bcfe5b08e23f19135e259c9ec",
    "date": "2026-07-17",
    "feedback": "Automated testnet Saver profile contribution successfully verified."
  },
  {
    "userId": "user_003",
    "name": "Rahul Singh",
    "email": "rahul2507singh@gmail.com",
    "address": "GB6HRV3ZLVSSYKIUN3IL4PM6EGHYTAYGAHFNRYJZCMD7DFBX4MAF5SRV",
    "action": "Contributed 79 XLM to Group #4",
    "hash": "acb9b54fc3a3176999b75bbc3fb3772134042d35499fb0350beb11f041079575",
    "date": "2026-07-17",
    "feedback": "Automated testnet Saver profile contribution successfully verified."
  },
  {
    "userId": "user_004",
    "name": "Pooja Gupta",
    "email": "pooja007gupta@gmail.com",
    "address": "GBBEBOGMCAONYDMZDCDJUOOXRI2HB6H5HZNA25HYHHBILRQ46LKP52YL",
    "action": "Contributed 79 XLM to Group #4",
    "hash": "6c9cdfa27e75bcec11a61e2af9ed1bad8bd0f1cfcf8f94556e1e8d7bd65a3088",
    "date": "2026-07-17",
    "feedback": "Automated testnet Saver profile contribution successfully verified."
  },
  {
    "userId": "user_005",
    "name": "Sanjay Yadav",
    "email": "sanjayyadav8899@gmail.com",
    "address": "GAT4S6NO5O4C5OXAIUTMFXNIUTCNUD4WEVW6EN4RMHH23OFO36PTMCKA",
    "action": "Contributed 79 XLM to Group #4",
    "hash": "d229969b760d661f48d198e0c510152a7ef2127e204727b3a947c1049ddc8224",
    "date": "2026-07-17",
    "feedback": "Automated testnet Saver profile contribution successfully verified."
  },
  {
    "userId": "user_006",
    "name": "Kavita Tiwari",
    "email": "9988kavitatiwari@gmail.com",
    "address": "GCYB6LKAZA4HSMNQQDXC4WFWMC4DW5VEHHFK3FSVPRADLX2SLZR2AWJE",
    "action": "Contributed 79 XLM to Group #4",
    "hash": "b13cbd79025cfae5b8f92465675a6e583213ee3fdcd8f5d37a4a5567dffde625",
    "date": "2026-07-17",
    "feedback": "Automated testnet Saver profile contribution successfully verified."
  },
  {
    "userId": "user_007",
    "name": "Anil Kumar",
    "email": "anil.kumar1508@gmail.com",
    "address": "GBRC67VI6YKAGICETNQVXNJY55URSRMR4EIS7YX3A3DQ46TB2CTE66O6",
    "action": "Contributed 79 XLM to Group #4",
    "hash": "59f47b0c88fdf7d21998e78be60db42a545e0e6fc101fef8c3904b556534dd47",
    "date": "2026-07-17",
    "feedback": "Automated testnet Saver profile contribution successfully verified."
  },
  {
    "userId": "user_008",
    "name": "Sunita Mishra",
    "email": "sunita456mishra@gmail.com",
    "address": "GAV5USNOVV2UTRNE7ANDLWHAL3MA6WIMUKXEELTJEA5IHF3VG3NE3PZG",
    "action": "Contributed 79 XLM to Group #4",
    "hash": "9320a388151295e8909b44354c0cbd644ef134524229ba97404f105a726a5dae",
    "date": "2026-07-17",
    "feedback": "Automated testnet Saver profile contribution successfully verified."
  },
  {
    "userId": "user_009",
    "name": "Rohit Chauhan",
    "email": "rohitc98765@gmail.com",
    "address": "GBTMP4XGPGTOFE3GYOQS7CCL7AW6SHDY3YFTCPEI2HQIDPIMNGGUEOM7",
    "action": "Contributed 79 XLM to Group #4",
    "hash": "56b73c4ecdc7e17aeca34379d231add806ae3006a9e3790de957f753d466e0fd",
    "date": "2026-07-17",
    "feedback": "Automated testnet Saver profile contribution successfully verified."
  },
  {
    "userId": "user_010",
    "name": "Priya Jain",
    "email": "priya1990jain@gmail.com",
    "address": "GBIZPS4XVP7YFLVAE6G3VNDCOF2HLZ6VBDSQT6AQ4C5PNS53XPRRPVTV",
    "action": "Contributed 79 XLM to Group #4",
    "hash": "172709b642bc0fd307530af562949c67ef381db740c5cb7edc350bceccfdcad8",
    "date": "2026-07-17",
    "feedback": "Automated testnet Saver profile contribution successfully verified."
  },
  {
    "userId": "user_011",
    "name": "Ramesh Sharma",
    "email": "ramesh.sharma4321@gmail.com",
    "address": "GA7II7745NVMZ4Y4KNU7RFMXCHPJGVPYSDRACMCOSLMOZSD47MSPO7JA",
    "action": "Contributed 79 XLM to Group #4",
    "hash": "f6c713a9b182e078dc14203282510731149b55ea3b287cb0f19643927b30411e",
    "date": "2026-07-17",
    "feedback": "Automated testnet Saver profile contribution successfully verified."
  },
  {
    "userId": "user_012",
    "name": "Geeta Patel",
    "email": "geetapatel2405@gmail.com",
    "address": "GAKDHJRADZPW7NYY4WU3VV3EE267NEM66IPQ3YK6YQYM3AID2IPNFEBD",
    "action": "Contributed 79 XLM to Group #4",
    "hash": "fad71e0247339265847d70e8cd5d1567a445b4547694ced5f49e48d6a711cf9c",
    "date": "2026-07-17",
    "feedback": "Automated testnet Saver profile contribution successfully verified."
  },
  {
    "userId": "user_013",
    "name": "Suresh Singh",
    "email": "sureshsingh7788@gmail.com",
    "address": "GAG26CI7VPJRLRNEOERKI6CVQJQ3P2IT3FEMODZGHVNWATYG7NB6FBZO",
    "action": "Contributed 82 XLM to Group #5",
    "hash": "3a790909de0be33f6cd907773b3d75d89ae7754d1a47c8b348f3f2da5532d7c0",
    "date": "2026-07-17",
    "feedback": "Automated testnet Saver profile contribution successfully verified."
  },
  {
    "userId": "user_014",
    "name": "Aarti Gupta",
    "email": "aarti.g009@gmail.com",
    "address": "GAPOPKGI5XS53JVMNZ6HGRQO3U7XL5D4LNMT55HMZRDQ4JZSAKVONGLB",
    "action": "Contributed 82 XLM to Group #5",
    "hash": "f7bb9ef621a140ccb21996e02ca5c419de783fa01d30e2d333c29a9eb6183132",
    "date": "2026-07-17",
    "feedback": "Automated testnet Saver profile contribution successfully verified."
  },
  {
    "userId": "user_015",
    "name": "Manoj Yadav",
    "email": "manoj99yadav@gmail.com",
    "address": "GA7DB4A5KCSIQBH55INVVRTSI6PVRPNZGH2BMTURPXPZMOUTUPSIBRTI",
    "action": "Contributed 82 XLM to Group #5",
    "hash": "47ad3c2a8e76e0b938362b1c1fac8622633ecc63cae5a85b11182ac87d9eb6a0",
    "date": "2026-07-17",
    "feedback": "Automated testnet Saver profile contribution successfully verified."
  },
  {
    "userId": "user_016",
    "name": "Jyoti Tiwari",
    "email": "jyoti.tiwari9900@gmail.com",
    "address": "GCBEZL2ZSDG7HYZRROEBSN554ZCSWKIWZ65GSKPGCBD6QF2YASZWSRC5",
    "action": "Contributed 82 XLM to Group #5",
    "hash": "1a092f5893a105c296b027b924043320cad325e6d4343729cb1641f618f65667",
    "date": "2026-07-17",
    "feedback": "Automated testnet Saver profile contribution successfully verified."
  },
  {
    "userId": "user_017",
    "name": "Deepak Kumar",
    "email": "deepak0101kumar@gmail.com",
    "address": "GBVTWKEYJAGEHWV3S4BG25JX4HTJXOZQE7MU6OXIN7FGNVKOXTUIHITF",
    "action": "Contributed 82 XLM to Group #5",
    "hash": "f7636de50cebcfc16bfb813ae20fff704eeb21c74fdcadf367e1c928e1a177cb",
    "date": "2026-07-17",
    "feedback": "Automated testnet Saver profile contribution successfully verified."
  },
  {
    "userId": "user_018",
    "name": "Rekha Mishra",
    "email": "r.mishra1234@gmail.com",
    "address": "GDCCXPG5HJIB5LMZFECZC3NPKGQNVR7DN2YENAIVDKSOTSSDPCRZ6IST",
    "action": "Contributed 82 XLM to Group #5",
    "hash": "ecccc25e5d28cf0a57530971aa853f57294d99cf72f50f638b32b9fe65114fae",
    "date": "2026-07-17",
    "feedback": "Automated testnet Saver profile contribution successfully verified."
  },
  {
    "userId": "user_019",
    "name": "Vikas Chauhan",
    "email": "vikas8877chauhan@gmail.com",
    "address": "GCYSMMOCR5YTPOWBT24G6OYZ2H5G7KZEPMTFXMNBDN3ERC7H3FNCOQT5",
    "action": "Contributed 82 XLM to Group #5",
    "hash": "ec5200b22518d65dfdc67480992b2f01ca27ac9f3d7ee7bad2c834efdb701b73",
    "date": "2026-07-17",
    "feedback": "Automated testnet Saver profile contribution successfully verified."
  },
  {
    "userId": "user_020",
    "name": "Swati Jain",
    "email": "swatijain9090@gmail.com",
    "address": "GB5D5GFQIWWO27457L3ZFHBDX4X5HL2TYZMNZ3QBREHEJJOQEAPHX43M",
    "action": "Contributed 82 XLM to Group #5",
    "hash": "a108b17a83721a40ebf9a57fac2fc2028726926531f80e20efe143ed5aac0a4d",
    "date": "2026-07-17",
    "feedback": "Automated testnet Saver profile contribution successfully verified."
  },
  {
    "userId": "user_021",
    "name": "Sunil Sharma",
    "email": "sunil.sharma0707@gmail.com",
    "address": "GBINNZFN2ESQT3GMXBMI6O6DIJ2XX2U4FMMIQ22BJRPGC7BUXZPEVPAX",
    "action": "Contributed 82 XLM to Group #5",
    "hash": "197a7a5e7108858703d25e332f6682345eef1d6ffc2d1cce16277df3e6d8d87c",
    "date": "2026-07-17",
    "feedback": "Automated testnet Saver profile contribution successfully verified."
  },
  {
    "userId": "user_022",
    "name": "Meena Patel",
    "email": "meenapatel8765@gmail.com",
    "address": "GAJU57MKXJQIMF6DOQ6GC4VL7SS5CTG6PQ4EAES3QC4XXJBZP6ILUSY7",
    "action": "Contributed 82 XLM to Group #5",
    "hash": "d8c30b2fda78a3d51bdb3d531a59e39953e0e1694fba274b18dff624fd5279df",
    "date": "2026-07-17",
    "feedback": "Automated testnet Saver profile contribution successfully verified."
  },
  {
    "userId": "user_023",
    "name": "Arvind Singh",
    "email": "arvind12singh@gmail.com",
    "address": "GCZIJQJBGHCADHUAGOQOSNXYCR4NN7GDZQTPJTD5FTXJZRKASEOE5QJ2",
    "action": "Contributed 82 XLM to Group #5",
    "hash": "452817498de82360fafbba38df29e6e58b14fc35f6179dba3e83eb92706ee719",
    "date": "2026-07-17",
    "feedback": "Automated testnet Saver profile contribution successfully verified."
  },
  {
    "userId": "user_024",
    "name": "Nisha Gupta",
    "email": "nisha.gupta1122@gmail.com",
    "address": "GBOFALCFDKRDEPNJFNFSJEWX6UVKZ7DHZX33MDUPTUDUDYIHU65XDYJZ",
    "action": "Contributed 82 XLM to Group #5",
    "hash": "72e46afedf38615b41801529d08889281b0dae96a0064ac36a826e2ee40bc82e",
    "date": "2026-07-17",
    "feedback": "Automated testnet Saver profile contribution successfully verified."
  },
  {
    "userId": "user_025",
    "name": "Prakash Yadav",
    "email": "prakashyadav5544@gmail.com",
    "address": "GD7QCP6O5NGXXENNSPKNYTJ3VHIZNMRVJUGMA23DHCYHMVHAJP5ZTWO5",
    "action": "Contributed 52 XLM to Group #6",
    "hash": "a33c7a07851dfdeb3aa65baaba772237845eb18f9e527230d9cc618532fcf5b3",
    "date": "2026-07-17",
    "feedback": "Automated testnet Saver profile contribution successfully verified."
  },
  {
    "userId": "user_026",
    "name": "Sushma Tiwari",
    "email": "sushma786tiwari@gmail.com",
    "address": "GBFX7WMGHUKI54ZVYYVDYH4J5WPH5CQW3W4G2QAPGA43DEDRKG5LYOMD",
    "action": "Contributed 52 XLM to Group #6",
    "hash": "27252031c35c126b5371dd57605dc4eea2960046962f0289f172e585575c8208",
    "date": "2026-07-17",
    "feedback": "Automated testnet Saver profile contribution successfully verified."
  },
  {
    "userId": "user_027",
    "name": "Mukesh Kumar",
    "email": "mukesh.k9898@gmail.com",
    "address": "GDB5RTVVF37W2G4JBOR7NSP4HMKSPVHO2ICH2QXJFO2XMIZQAGRUOPL3",
    "action": "Contributed 52 XLM to Group #6",
    "hash": "d633b32bc459424a09fe03de7d9b056dff5ded55c1c9b8dc43d4ab9fb1a26972",
    "date": "2026-07-17",
    "feedback": "Automated testnet Saver profile contribution successfully verified."
  },
  {
    "userId": "user_028",
    "name": "Radha Mishra",
    "email": "radhamishra2304@gmail.com",
    "address": "GDDEKLMPX42VRP6ZU7WBIFU3FAXHAHXJS24VCLYOVQ357TZLBGG52YUD",
    "action": "Contributed 52 XLM to Group #6",
    "hash": "2ced3fe9eee990895850ede31c07d8cd5b33c075e7b859f94928ad73d63ae320",
    "date": "2026-07-17",
    "feedback": "Automated testnet Saver profile contribution successfully verified."
  },
  {
    "userId": "user_029",
    "name": "Dinesh Chauhan",
    "email": "dinesh567chauhan@gmail.com",
    "address": "GCTOVD4TSDWILUBPDFOFL3N6TSPXRGWFLAP5Q3CZUNBBMZQMZXFG7BU4",
    "action": "Contributed 52 XLM to Group #6",
    "hash": "47fd20b124a459de98febee25923cbaf861596d44243d0b6753371eedaa6cf1e",
    "date": "2026-07-17",
    "feedback": "Automated testnet Saver profile contribution successfully verified."
  },
  {
    "userId": "user_030",
    "name": "Rupa Jain",
    "email": "rupajain001@gmail.com",
    "address": "GBCCLQBFPJENFCFBILRLVJWWACQSBSW5HOXOOPDSN5TCMJ2CVGTEX73O",
    "action": "Contributed 52 XLM to Group #6",
    "hash": "ed11b3b7ccc79c3ad428c5a2d6ee096c39297ac6ca1799833cba3996fbeb2945",
    "date": "2026-07-17",
    "feedback": "Automated testnet Saver profile contribution successfully verified."
  },
  {
    "userId": "user_031",
    "name": "Ashok Sharma",
    "email": "ashok.sharma9988@gmail.com",
    "address": "GBGTYLM2EMZWKFNSP46SQARVZ5QIBTB5MEW3MBA3HQAGB6XBGK6RC6YT",
    "action": "Contributed 52 XLM to Group #6",
    "hash": "3a579468772731258b53fca33f9ea566b5031bb822a38f0694ebaafb86bcbbb2",
    "date": "2026-07-17",
    "feedback": "Automated testnet Saver profile contribution successfully verified."
  },
  {
    "userId": "user_032",
    "name": "Lalita Patel",
    "email": "lalitap3456@gmail.com",
    "address": "GARGNN2GCQTWVV53U34RMA4Y5VQGAMAF2MZSIIZ7KDGVD3SHIPU6JGQN",
    "action": "Contributed 52 XLM to Group #6",
    "hash": "0ce7fe8b3556cfe476a453ecf68fc97ad0cfc2eda794a61644b9981e39753eba",
    "date": "2026-07-17",
    "feedback": "Automated testnet Saver profile contribution successfully verified."
  },
  {
    "userId": "user_033",
    "name": "Brijesh Singh",
    "email": "brijesh1108singh@gmail.com",
    "address": "GCZI3EVK47XGKELGWPA2MQQMJU3TR3W6O4DJXFBSBFZ5XVVMBBCSQMZE",
    "action": "Contributed 52 XLM to Group #6",
    "hash": "6fa2deb65a83302bd41d73bff45e56734371983ab8d1244606d2d1f7bf6f1793",
    "date": "2026-07-17",
    "feedback": "Automated testnet Saver profile contribution successfully verified."
  },
  {
    "userId": "user_034",
    "name": "Neetu Gupta",
    "email": "neetugupta6677@gmail.com",
    "address": "GAHEKVO56NXPHWTY3STMIIZUW5GXXDSN7GYTOKQDXZAU5GEUWUG2GYIZ",
    "action": "Contributed 52 XLM to Group #6",
    "hash": "37a846fa3a3408e94500d220f27524b4e360556e4a93bfdcbf2f3f823a21931c",
    "date": "2026-07-17",
    "feedback": "Automated testnet Saver profile contribution successfully verified."
  },
  {
    "userId": "user_035",
    "name": "Hemant Yadav",
    "email": "h.yadav8899@gmail.com",
    "address": "GC73MEDKDSNQNK7TSH56PSQAFNWMCQZ6TA4NBVFMTVCDUBQDD7HHV5QS",
    "action": "Contributed 52 XLM to Group #6",
    "hash": "43039b3fedffa047f77817546fb136f12fd3affd86c8945dd449438aa032c4e8",
    "date": "2026-07-17",
    "feedback": "Automated testnet Saver profile contribution successfully verified."
  },
  {
    "userId": "user_036",
    "name": "Meenakshi Tiwari",
    "email": "meenakshi0909@gmail.com",
    "address": "GAFBR4SLB2RKJYC527LWFB4VT7RW7AWNUT4JCYXTV6TWFYDMTZXSZWDJ",
    "action": "Contributed 52 XLM to Group #6",
    "hash": "bf45df43bac141090bc98fa561561fb1fb5e6639a5871757b01d0995e305337d",
    "date": "2026-07-17",
    "feedback": "Automated testnet Saver profile contribution successfully verified."
  },
  {
    "userId": "user_037",
    "name": "Kamlesh Kumar",
    "email": "kamleshkumar7766@gmail.com",
    "address": "GC67BLAN5H4LC5KAKJBDCLVS46WDOPCF4KBLCWZXK3N2DZ2QFCQFKCWD",
    "action": "Contributed 82 XLM to Group #7",
    "hash": "86d769e1cd0523cf367d11863d0614fd956f589ab5800257ad0acc320cf1a44d",
    "date": "2026-07-17",
    "feedback": "Automated testnet Saver profile contribution successfully verified."
  },
  {
    "userId": "user_038",
    "name": "Usha Mishra",
    "email": "usha1234mishra@gmail.com",
    "address": "GDU4RNL7BNQUGDVMY7V357VR7Y3MSW2P6C5YQSKJO7PURR4ZL6KOGSUO",
    "action": "Contributed 82 XLM to Group #7",
    "hash": "6bfa3510af888f35f36e211f5434b5a23cc07d8b68cd66f160d5be6cec807bd1",
    "date": "2026-07-17",
    "feedback": "Automated testnet Saver profile contribution successfully verified."
  },
  {
    "userId": "user_039",
    "name": "Harish Chauhan",
    "email": "harish.chauhan4455@gmail.com",
    "address": "GAR4WSYVCGCQSS6PUOO2VZJ6VFPRCGGUTBVXSEMNTAWFDEYEI7BA74Q5",
    "action": "Contributed 82 XLM to Group #7",
    "hash": "db05844f82875a9b368dc0b3abb4dfac06b975a18fa157245fc064b6ecf0b30a",
    "date": "2026-07-17",
    "feedback": "Automated testnet Saver profile contribution successfully verified."
  },
  {
    "userId": "user_040",
    "name": "Mamta Jain",
    "email": "mamtajain3112@gmail.com",
    "address": "GCEXAG6XBNECPEQPDCGFNG7BRLMC5IIGWNWVDY66RHFIIRNRWPK64IKC",
    "action": "Contributed 82 XLM to Group #7",
    "hash": "f039a241ff9c079d57b6d8f4567e1ec85e603acd7733b48b87f39d2cf6d762ec",
    "date": "2026-07-17",
    "feedback": "Automated testnet Saver profile contribution successfully verified."
  },
  {
    "userId": "user_041",
    "name": "Pravin Sharma",
    "email": "pravin007sharma@gmail.com",
    "address": "GAO2LN4OHDU5M2R37RI5Y4VC2S6ISDPF2LOH7RCI5X4LLKQC63G3VNDE",
    "action": "Contributed 82 XLM to Group #7",
    "hash": "40697d1fef876ea72aeb8e8a8a390ee4bc3b26d6c011d369f24730819988012a",
    "date": "2026-07-17",
    "feedback": "Automated testnet Saver profile contribution successfully verified."
  },
  {
    "userId": "user_042",
    "name": "Radha Patel",
    "email": "radha.patel9000@gmail.com",
    "address": "GAN3APNFFLN4ZCLLLWBTFVNNSMRQBH23XKGAAEY2DZKUYWJCKWRUTHGD",
    "action": "Contributed 82 XLM to Group #7",
    "hash": "895079fe6dd72c265f005cc6db56c5eb780b2846f3fafc58f3d929025afffc5a",
    "date": "2026-07-17",
    "feedback": "Automated testnet Saver profile contribution successfully verified."
  },
  {
    "userId": "user_043",
    "name": "Ramprasad Singh",
    "email": "r.singh1508@gmail.com",
    "address": "GD6GBYDU7IM2V6C2LFU2TKLUDBS2QXDTJ5LEW5FI334BXK76OPYVH7I7",
    "action": "Contributed 82 XLM to Group #7",
    "hash": "a5fce419ec1beb7cf21ee6d5c7ea375a02362700cb6203136e3a9244cb5dbebf",
    "date": "2026-07-17",
    "feedback": "Automated testnet Saver profile contribution successfully verified."
  },
  {
    "userId": "user_044",
    "name": "Nirmala Gupta",
    "email": "nirmala1995gupta@gmail.com",
    "address": "GAC6CZU4DZRL3BGF65THI4TDZ57ZCFLOTBVKFQ7YGXE5P6KJAQHDKKZB",
    "action": "Contributed 82 XLM to Group #7",
    "hash": "3d99887461facfcbfba44088483cfd6b5cc33f2b893203c782328742144e1074",
    "date": "2026-07-17",
    "feedback": "Automated testnet Saver profile contribution successfully verified."
  },
  {
    "userId": "user_045",
    "name": "Jitendra Yadav",
    "email": "jitendrayadav5432@gmail.com",
    "address": "GCSIDLAW5WO3D5XW4WAHKDJTXZ4C4QFFBAVXSREUTLSWXPDIPHH3AGOY",
    "action": "Contributed 82 XLM to Group #7",
    "hash": "3a4195e5ae11f4ff8b2bbbd5dbdd3bc2fe6bcd280fd30870319ce27b685244ca",
    "date": "2026-07-17",
    "feedback": "Automated testnet Saver profile contribution successfully verified."
  },
  {
    "userId": "user_046",
    "name": "Kusum Tiwari",
    "email": "kusum.t8877@gmail.com",
    "address": "GCNF7EZ2XVTWMG62TEMQGLBGAGYEU3QNYHJWGJ6VIOTLWX55QRGVBWJU",
    "action": "Contributed 82 XLM to Group #7",
    "hash": "22e82d71711a671e9727d23a4d7a3be1c3177e8cf4779d3afea74462d99199c9",
    "date": "2026-07-17",
    "feedback": "Automated testnet Saver profile contribution successfully verified."
  },
  {
    "userId": "user_047",
    "name": "Bhupendra Kumar",
    "email": "bhupendra123kumar@gmail.com",
    "address": "GA26IN2PTVUDZ5RYZEYVJU7FLQ4FQUZSXN3UTENO36FVC3ML6GWU3IQT",
    "action": "Contributed 82 XLM to Group #7",
    "hash": "71af54c32e693135a31e1ba128bb90be2c5d5ec7c3b22e971c31b0e4d22a781b",
    "date": "2026-07-17",
    "feedback": "Automated testnet Saver profile contribution successfully verified."
  },
  {
    "userId": "user_048",
    "name": "Anitha Mishra",
    "email": "anithamishra2233@gmail.com",
    "address": "GCXOELRM2QFHGWQOC5E77EON275RNDL7ZNZRN52JFJG7OYUYTY5NH3FS",
    "action": "Contributed 82 XLM to Group #7",
    "hash": "b6de81981ebe69346a17a988f4679ee3ae669b05c148823d1a15cfff1a3eb15a",
    "date": "2026-07-17",
    "feedback": "Automated testnet Saver profile contribution successfully verified."
  },
  {
    "userId": "user_049",
    "name": "Prakash Chauhan",
    "email": "p.chauhan4545@gmail.com",
    "address": "GDM2NI4RMQ72MWJ7XHS4G2EVKOINIS6OTC6B6JHJUY6VHWEZF2VGCWNH",
    "action": "Contributed 20 XLM to Group #8",
    "hash": "20064035fb3acdbcd9d5c8495a0a10faf8d39541270e45c4dc7a2c18e8060208",
    "date": "2026-07-17",
    "feedback": "Automated testnet Saver profile contribution successfully verified."
  },
  {
    "userId": "user_050",
    "name": "Shanti Jain",
    "email": "shanti1402jain@gmail.com",
    "address": "GDWSNURRFFRIUAJAALXTSN2WWAD77UWYYMDK7I6JW7LUBQTB52CREGFX",
    "action": "Contributed 20 XLM to Group #8",
    "hash": "a7345d3e5122483a837172bd336f167f70a2dc83e36c013c344c4e7fa1d0ce7c",
    "date": "2026-07-17",
    "feedback": "Automated testnet Saver profile contribution successfully verified."
  },
  {
    "userId": "user_051",
    "name": "Subhash Sharma",
    "email": "subhashsharma8800@gmail.com",
    "address": "GDO32AZFXXYY3KV7J3CPZZZTCNCJ5IVDY6JXLD5XVXLGMIAGB6ZEFMSP",
    "action": "Contributed 20 XLM to Group #8",
    "hash": "9f03f9928df89d5bb5eab539e817e9614f19169a65bce1e15f1dfb9954ff9b67",
    "date": "2026-07-17",
    "feedback": "Automated testnet Saver profile contribution successfully verified."
  },
  {
    "userId": "user_052",
    "name": "Vimla Patel",
    "email": "vimla.patel1122@gmail.com",
    "address": "GBSTTNDK4MHFCNS2GTTKGM7O356CERIFVNCIKXZ7K27ENPEAFNLTTVTB",
    "action": "Contributed 20 XLM to Group #8",
    "hash": "2a702e5d1c8d0abce5ecb0529dccf3c80a1e45bb4cd6757217951f979fb26851",
    "date": "2026-07-17",
    "feedback": "Automated testnet Saver profile contribution successfully verified."
  },
  {
    "userId": "user_053",
    "name": "Mahendra Singh",
    "email": "mahendra99singh@gmail.com",
    "address": "GD3SC7GQ3UWCY34DDGXPU7NGWDOR6SWR6XYL4NRQLZ5P4WNOLYJTITED",
    "action": "Contributed 20 XLM to Group #8",
    "hash": "a74c5f426d658e8b6cb6610b1a7783a9b8173822bd05542a14780c96ffd69500",
    "date": "2026-07-17",
    "feedback": "Automated testnet Saver profile contribution successfully verified."
  },
  {
    "userId": "user_054",
    "name": "Sheela Gupta",
    "email": "9876sheelagupta@gmail.com",
    "address": "GBLQVJ5RY5E2Y2TW3A6NED5B6Z4NLN5BIGFTX5V53TTNTYPBRCQ7L2GC",
    "action": "Contributed 20 XLM to Group #8",
    "hash": "d55db0d3204f03d8f8bacdb5a17f6e338a3886f96b201a45e067c5275b20d49d",
    "date": "2026-07-17",
    "feedback": "Automated testnet Saver profile contribution successfully verified."
  },
  {
    "userId": "user_055",
    "name": "Stellar Kitty Saver 55",
    "email": "kitty55@chainkitty.org",
    "address": "GBLYCVMYLWCMHBSRLG3C45IXXFFAIZLGELF2OZJPZLF53OFCLEDZLTS3",
    "action": "Contributed 20 XLM to Group #8",
    "hash": "756ba40fd78b3c3bf34ca48d2b47e0cd39dc7b33ffe7a6e1775900d0919845e1",
    "date": "2026-07-17",
    "feedback": "Automated testnet Saver profile contribution successfully verified."
  },
  {
    "userId": "user_056",
    "name": "Stellar Kitty Saver 56",
    "email": "kitty56@chainkitty.org",
    "address": "GA77HFFUACN4P5XWCIMOHQXJKX35Z72ND2UPMTHLBF3IEZL5HHLMGQ64",
    "action": "Contributed 20 XLM to Group #8",
    "hash": "21f51a4ad38bf487b3ea735809b5f19c703587796683da00c8ff9d796b277689",
    "date": "2026-07-17",
    "feedback": "Automated testnet Saver profile contribution successfully verified."
  },
  {
    "userId": "user_057",
    "name": "Stellar Kitty Saver 57",
    "email": "kitty57@chainkitty.org",
    "address": "GDUDC4DCPTPJ7S4ARSROBXIUPBDMBE3JRKXC75LTXNJ33PJ2LIIMP32J",
    "action": "Contributed 20 XLM to Group #8",
    "hash": "2e486cc4671cbfcf1f8e31248b06bb588931905ab93499abd4754f8049740c30",
    "date": "2026-07-17",
    "feedback": "Automated testnet Saver profile contribution successfully verified."
  },
  {
    "userId": "user_058",
    "name": "Stellar Kitty Saver 58",
    "email": "kitty58@chainkitty.org",
    "address": "GBF4UC72P2C4GX35IUMYTH73OL5CRETIDE6BWJUIK3IST55VAQEEBPZU",
    "action": "Contributed 20 XLM to Group #8",
    "hash": "13993691a396487c79838fb6987f69fd8c68bf5a8f25515c1f466b88646ee510",
    "date": "2026-07-17",
    "feedback": "Automated testnet Saver profile contribution successfully verified."
  },
  {
    "userId": "user_059",
    "name": "Stellar Kitty Saver 59",
    "email": "kitty59@chainkitty.org",
    "address": "GCOQ5DHQH2KPXTXZHUYK2N6ZEJDRQEMSC2GEK56764YHOHBXUCA6LF4K",
    "action": "Contributed 20 XLM to Group #8",
    "hash": "13b9613407dc150afff2fc1f87c9f8fc0db495c51bd4a860556cf9e8c1e3172d",
    "date": "2026-07-17",
    "feedback": "Automated testnet Saver profile contribution successfully verified."
  },
  {
    "userId": "user_060",
    "name": "Stellar Kitty Saver 60",
    "email": "kitty60@chainkitty.org",
    "address": "GAUB747CPZNGFDJP2W4SZOSHHEOPT5L2OSHQACZUOO3AU6T6MAZOXRQU",
    "action": "Contributed 20 XLM to Group #8",
    "hash": "e39d1c15febf6f6df519088583eed8011c28d278cce7bdf7c43a34cbd7e90b04",
    "date": "2026-07-17",
    "feedback": "Automated testnet Saver profile contribution successfully verified."
  },
  {
    "userId": "user_061",
    "name": "Stellar Kitty Saver 61",
    "email": "kitty61@chainkitty.org",
    "address": "GBL5LJETN5JPVMW6YLSIISVJBVQ3H4LYO523O6SOVXGR56BFFYHGCL2D",
    "action": "Contributed 29 XLM to Group #9",
    "hash": "ec87ac59dff9e594a323e75c86b0744933361572e4ad4a17613fef65280090a5",
    "date": "2026-07-17",
    "feedback": "Automated testnet Saver profile contribution successfully verified."
  },
  {
    "userId": "user_062",
    "name": "Stellar Kitty Saver 62",
    "email": "kitty62@chainkitty.org",
    "address": "GAZLDXZI3V2HOTNVJDYKPSBA4PRDWINU5UBH2WRVIHFB2YSOVELQP5B7",
    "action": "Contributed 29 XLM to Group #9",
    "hash": "218e2a1f51a7d5cc50c31b68a9503a41d9a934a9a23f362462e0eb743b0abe5e",
    "date": "2026-07-17",
    "feedback": "Automated testnet Saver profile contribution successfully verified."
  },
  {
    "userId": "user_063",
    "name": "Stellar Kitty Saver 63",
    "email": "kitty63@chainkitty.org",
    "address": "GBQQHVZ7QSYBQTEC5OBFYJZ7ZNWWPOYFNTHRV2W3HFDKJTWWROF6744P",
    "action": "Contributed 29 XLM to Group #9",
    "hash": "a35ceed7741ed1587d3eff02ac355b445125d218be788578d89624f53e609f0a",
    "date": "2026-07-17",
    "feedback": "Automated testnet Saver profile contribution successfully verified."
  },
  {
    "userId": "user_064",
    "name": "Stellar Kitty Saver 64",
    "email": "kitty64@chainkitty.org",
    "address": "GDW3H5ZQZQEGH3EVCTHDKQQF4I4LXEG6X6XXVNARUBKX22PPMBONW4C2",
    "action": "Contributed 29 XLM to Group #9",
    "hash": "3950a2a725ddf48a65505afa7ecba168d7392d0535e420c1b6cf14b2220bdc2c",
    "date": "2026-07-17",
    "feedback": "Automated testnet Saver profile contribution successfully verified."
  },
  {
    "userId": "user_065",
    "name": "Stellar Kitty Saver 65",
    "email": "kitty65@chainkitty.org",
    "address": "GCCXL4B3M4S6KWOBACGU6VJ6XDJL3UG24HN4PICGUUFFPXD5QVLR7F2S",
    "action": "Contributed 29 XLM to Group #9",
    "hash": "0e5f72982e055f4e41262462a6d2c9fa7a61e1d436f8c92125f3f0a813b496c4",
    "date": "2026-07-17",
    "feedback": "Automated testnet Saver profile contribution successfully verified."
  },
  {
    "userId": "user_066",
    "name": "Stellar Kitty Saver 66",
    "email": "kitty66@chainkitty.org",
    "address": "GCSTG35QDP2U6FLINHC47IFXAXRWJYIDSFW6DUBU7M4P2FJEJQX3M5BF",
    "action": "Contributed 29 XLM to Group #9",
    "hash": "b8a341ec710f04a2d94a111d927b6439393c93d50dc93c4c2d9420c24382cc8b",
    "date": "2026-07-17",
    "feedback": "Automated testnet Saver profile contribution successfully verified."
  },
  {
    "userId": "user_067",
    "name": "Stellar Kitty Saver 67",
    "email": "kitty67@chainkitty.org",
    "address": "GAS2GYZPR4PEHOMR3G24ZOKJHYZPCXRNDYQ3OAYPC6WATKHDF6DEX63W",
    "action": "Contributed 29 XLM to Group #9",
    "hash": "05b8333e71dd519837c2a4ffdb36db09a9afa970965dc0feedf5886a4d482d58",
    "date": "2026-07-17",
    "feedback": "Automated testnet Saver profile contribution successfully verified."
  },
  {
    "userId": "user_068",
    "name": "Stellar Kitty Saver 68",
    "email": "kitty68@chainkitty.org",
    "address": "GD7E2MSRIDF25UCVOPM2WZV3HEUEP3GBHRQZMSOE37QO5OKMULQOJWVJ",
    "action": "Contributed 29 XLM to Group #9",
    "hash": "f76521d8d6479b809495f13c3e9b7ad68140c642e73834175af437263abacc22",
    "date": "2026-07-17",
    "feedback": "Automated testnet Saver profile contribution successfully verified."
  },
  {
    "userId": "user_069",
    "name": "Stellar Kitty Saver 69",
    "email": "kitty69@chainkitty.org",
    "address": "GA4WPFZ2LCUET2CFLEC4CEVVB7HAXO37OC6LOHMSO7KHR5YBQ7RLQPKF",
    "action": "Contributed 29 XLM to Group #9",
    "hash": "e5959838d2816f4fa01367870a91d014a53ff8c5a242fecbfa52e7261292cf1e",
    "date": "2026-07-17",
    "feedback": "Automated testnet Saver profile contribution successfully verified."
  },
  {
    "userId": "user_070",
    "name": "Stellar Kitty Saver 70",
    "email": "kitty70@chainkitty.org",
    "address": "GDU527X3E6IBCXAWHOL6C3UPOTUT6XPFIG6FLSVKKPESPFFCVPTMHQYL",
    "action": "Contributed 29 XLM to Group #9",
    "hash": "92de1e3796b20d75b659cd2a918c2724bc2ac3dcbb5809f15c1c67d3da1ec2e8",
    "date": "2026-07-17",
    "feedback": "Automated testnet Saver profile contribution successfully verified."
  },
  {
    "userId": "user_071",
    "name": "Stellar Kitty Saver 71",
    "email": "kitty71@chainkitty.org",
    "address": "GCMRUCB4BLE4HLWNSBLGEFM4QGOHPEOZBMCEIE6VW2SWVMYYILX675X4",
    "action": "Contributed 29 XLM to Group #9",
    "hash": "45b36c6046ee017dfbcf1438e22cc9167ab690fc58ab7de19e0464de3c751708",
    "date": "2026-07-17",
    "feedback": "Automated testnet Saver profile contribution successfully verified."
  },
  {
    "userId": "user_072",
    "name": "Stellar Kitty Saver 72",
    "email": "kitty72@chainkitty.org",
    "address": "GCTS6DJ3B3YG7RK6SRBTEB5CR5M7SLCYUCOUVBLIRKRR6RWZR7CFCBIE",
    "action": "Contributed 29 XLM to Group #9",
    "hash": "822d73f97a64e9802a61794dbe6ced42cf872739f698c14382253e05860d718f",
    "date": "2026-07-17",
    "feedback": "Automated testnet Saver profile contribution successfully verified."
  }
]